ncEllipsisParser/__init__.py
ncEllipsisParser-0.0.2.dist-info/LICENSE
ncEllipsisParser-0.0.2.dist-info/METADATA
ncEllipsisParser-0.0.2.dist-info/WHEEL
ncEllipsisParser-0.0.2.dist-info/top_level.txt
ncEllipsisParser-0.0.2.dist-info/RECORD
