Metadata-Version: 2.1
Name: ncEllipsisParser
Version: 0.0.2
Summary: Package to parse a netCDF to an Ellipsis Drive data structure
Home-page: https://github.com/ellipsis-drive/ncEllipsisParser
Author: Daniel van der Maas
Author-email: daniel@ellipsis-drive.com
Classifier: Programming Language :: Python :: 3
Classifier: License :: OSI Approved :: MIT License
Classifier: Operating System :: OS Independent
Requires-Python: >=3.6
License-File: LICENSE
Requires-Dist: rasterio
Requires-Dist: xarray
Requires-Dist: numpy
Requires-Dist: ellipsis
